{"filename":"c:\\staging\\ofsPipelineFunctions\\__azurite_db_blob_extent__.json","collections":[{"name":"$EXTENTS_COLLECTION$","data":[{"id":"d7880316-6d9a-4b57-97b3-aca66fd1432c","locationId":"Default","path":"d7880316-6d9a-4b57-97b3-aca66fd1432c","size":1108,"lastModifiedInMS":1672770592383,"meta":{"revision":2,"created":1672770592383,"version":0,"updated":1672770613888},"$loki":1,"LastModifyInMS":1672770613888},{"id":"4c55fd6f-f916-4296-b821-813a7ba14fca","locationId":"Default","path":"4c55fd6f-f916-4296-b821-813a7ba14fca","size":3114,"lastModifiedInMS":1672779850986,"meta":{"revision":38,"created":1672779850986,"version":0,"updated":1672781006199},"$loki":2,"LastModifyInMS":1672781006199},{"id":"fd7ac7a8-0234-4c31-90c2-868bea2878a5","locationId":"Default","path":"fd7ac7a8-0234-4c31-90c2-868bea2878a5","size":6749,"lastModifiedInMS":1673289602266,"meta":{"revision":84,"created":1673289602267,"version":0,"updated":1673295579908},"$loki":19,"LastModifyInMS":1673295579908},{"id":"9f67c219-5ed9-4ebe-aa6b-18159a40d5fd","locationId":"Default","path":"9f67c219-5ed9-4ebe-aa6b-18159a40d5fd","size":228,"lastModifiedInMS":1673293601482,"meta":{"revision":2,"created":1673293601483,"version":0,"updated":1673295400329},"$loki":20,"LastModifyInMS":1673295400329},{"id":"5c03270b-3804-4363-aa74-ee3b8305a392","locationId":"Default","path":"5c03270b-3804-4363-aa74-ee3b8305a392","size":1028,"lastModifiedInMS":1673295778938,"meta":{"revision":11,"created":1673295778938,"version":0,"updated":1673295889994},"$loki":21,"LastModifyInMS":1673295889994},{"id":"464ea4a0-7b0d-4448-99fe-afa6aede16e6","locationId":"Default","path":"464ea4a0-7b0d-4448-99fe-afa6aede16e6","size":76,"lastModifiedInMS":1673295797299,"meta":{"revision":0,"created":1673295797299,"version":0},"$loki":22}],"idIndex":[1,2,19,20,21,22],"binaryIndices":{"id":{"name":"id","dirty":false,"values":[5,1,4,3,0,2]}},"constraints":null,"uniqueNames":[],"transforms":{},"objType":"$EXTENTS_COLLECTION$","dirty":false,"cachedIndex":null,"cachedBinaryIndex":null,"cachedData":null,"adaptiveBinaryIndices":true,"transactional":false,"cloneObjects":false,"cloneMethod":"parse-stringify","asyncListeners":false,"disableMeta":false,"disableChangesApi":true,"disableDeltaChangesApi":true,"autoupdate":false,"serializableIndices":true,"disableFreeze":true,"ttl":null,"maxId":22,"DynamicViews":[],"events":{"insert":[],"update":[],"pre-insert":[],"pre-update":[],"close":[],"flushbuffer":[],"error":[],"delete":[null],"warning":[null]},"changes":[],"dirtyIds":[]}],"databaseVersion":1.5,"engineVersion":1.5,"autosave":true,"autosaveInterval":5000,"autosaveHandle":null,"throttledSaves":true,"options":{"autosave":true,"autosaveInterval":5000,"serializationMethod":"normal","destructureDelimiter":"$<\n"},"persistenceMethod":"fs","persistenceAdapter":null,"verbose":false,"events":{"init":[null],"loaded":[],"flushChanges":[],"close":[],"changes":[],"warning":[]},"ENV":"NODEJS"}